{
  "name": "TContainerLoad",
  "base": "PersistedModel",
  "idInjection": false,
  "options": {
    "validateUpsert": true
  },
  "mysql": {
    "schema": "arbulk",
    "table": "t_container_load"
  },
  "properties": {
    "id": {
      "type": "Number",
      "id": true,
      "required": true,
      "length": null,
      "precision": 10,
      "scale": 0,
      "mysql": {
        "columnName": "id",
        "dataType": "int",
        "dataLength": null,
        "dataPrecision": 10,
        "dataScale": 0,
        "nullable": "N"
      },
      "_selectable": false
    },
    "lotId": {
      "type": "Number",
      "required": false,
      "length": null,
      "precision": 10,
      "scale": 0,
      "mysql": {
        "columnName": "load_lot_id",
        "dataType": "int",
        "dataLength": null,
        "dataPrecision": 10,
        "dataScale": 0,
        "nullable": "Y"
      },
      "_selectable": true
    },
    "loadContId": {
      "type": "Number",
      "required": false,
      "length": null,
      "precision": 10,
      "scale": 0,
      "mysql": {
        "columnName": "load_container_id",
        "dataType": "int",
        "dataLength": null,
        "dataPrecision": 10,
        "dataScale": 0,
        "nullable": "Y"
      },
      "_selectable": true
    },
    "loadContDId": {
      "type": "Number",
      "required": false,
      "length": null,
      "precision": 10,
      "scale": 0,
      "mysql": {
        "columnName": "load_domestic_id",
        "dataType": "int",
        "dataLength": null,
        "dataPrecision": 10,
        "dataScale": 0,
        "nullable": "Y"
      },
      "_selectable": true
    },
    "piInventId": {
      "type": "Number",
      "required": false,
      "length": null,
      "precision": 10,
      "scale": 0,
      "mysql": {
        "columnName": "piInventory_id",
        "dataType": "int",
        "dataLength": null,
        "dataPrecision": 10,
        "dataScale": 0,
        "nullable": "Y"
      },
      "_selectable": true
    },
    "invLocId": {
      "type": "Number",
      "required": false,
      "length": null,
      "precision": 10,
      "scale": 0,
      "mysql": {
        "columnName": "inv_loc_id",
        "dataType": "int",
        "dataLength": null,
        "dataPrecision": 10,
        "dataScale": 0,
        "nullable": "Y"
      },
      "_selectable": true
    },
    "noOfBags": {
      "type": "Number",
      "required": false,
      "length": null,
      "precision": 10,
      "scale": 0,
      "mysql": {
        "columnName": "no_of_bags",
        "dataType": "int",
        "dataLength": null,
        "dataPrecision": 10,
        "dataScale": 0,
        "nullable": "Y"
      },
      "_selectable": true
    },
    "weight": {
      "type": "Number",
      "required": false,
      "length": null,
      "precision": 10,
      "scale": 0,
      "mysql": {
        "columnName": "weight",
        "dataType": "int",
        "dataLength": null,
        "dataPrecision": 10,
        "dataScale": 0,
        "nullable": "Y"
      },
      "_selectable": true
    },
    "createdBy": {
      "type": "Number",
      "required": false,
      "length": null,
      "precision": 10,
      "scale": 0,
      "mysql": {
        "columnName": "created_by",
        "dataType": "int",
        "dataLength": null,
        "dataPrecision": 10,
        "dataScale": 0,
        "nullable": "Y"
      },
      "_selectable": true
    },
    "active": {
      "type": "Number",
      "required": false,
      "length": null,
      "precision": 3,
      "scale": 0,
      "mysql": {
        "columnName": "active",
        "dataType": "tinyint",
        "dataLength": null,
        "dataPrecision": 3,
        "dataScale": 0,
        "nullable": "Y"
      },
      "_selectable": true
    }
  },
  "validations": [],
  "relations": {

    "TPackagingInstructionLots": {
      "type": "belongsTo",
      "model": "TPackagingInstructionLots",
      "foreignKey": "lotId"
    },

    "TInventoryLocation": {
      "type": "belongsTo",
      "model": "TInventoryLocation",
      "foreignKey": "invLocId"
    },
    "TContainerInternational": {
      "type": "belongsTo",
      "model": "TContainerInternational",
      "foreignKey": "loadContId"
    },
    "TContainerDomestic": {
      "type": "belongsTo",
      "model": "TContainerDomestic",
      "foreignKey": "loadContDId"
    }

  },
  "acls": [],
  "methods": {}
}
